<mvc:View xmlns:core="sap.ui.core" xmlns:mvc="sap.ui.core.mvc" xmlns="sap.m" controllerName="zecp.controller.AgreementInquiryList"
	xmlns:html="http://www.w3.org/1999/xhtml" xmlns:l="sap.ui.layout" xmlns:uxap="sap.uxap" xmlns:f="sap.ui.layout.form" xmlns:tnt="sap.tnt"
	xmlns:table="sap.ui.table">
	<core:Fragment fragmentName="zecp.view.fragments.ToolHeader" type="XML"/>
	<uxap:ObjectPageLayout id="ObjectAgreementList" enableLazyLoading="true">
		<uxap:sections>
			<uxap:ObjectPageSection title="{i18n>AgreementInquiry}">
				<uxap:subSections>
					<uxap:ObjectPageSubSection title=" ">
						<uxap:blocks>
							<VBox class="sapUiLargeMarginBottom">
								<MessageStrip id="idAgrInqMsgStrp" text="" showIcon="true" showCloseButton="true" class="sapUiMediumMarginBottom" visible="false"></MessageStrip>
								<f:SimpleForm id="SimpleFormChange354" editable="true" layout="ResponsiveGridLayout" title="" labelSpanXL="4" labelSpanL="4" labelSpanM="3"
									labelSpanS="12" adjustLabelSpan="false" emptySpanXL="2" emptySpanL="2" emptySpanM="0" emptySpanS="0" columnsXL="2" columnsL="2" columnsM="2"
									singleContainerFullSize="false">
									<f:content>
										<core:Title text="{i18n>EnterVinOrAgreement}"/>
										<Label text="{i18n>SearchBy}" textAlign="Begin"/>
										<RadioButtonGroup selectedIndex="0" columns="2" id="idSearchByRadio" select="onSelectSearchBy">
											<buttons>
												<RadioButton text="{i18n>Agreement#}"/>
												<RadioButton text=" {i18n>VIN}"/>
											</buttons>
										</RadioButtonGroup>
										<Label text="{i18n>Agreement#}" textAlign="Begin" id="idInqLabel" textDirection="LTR"/>
										<Input value="{LocalDataModel>/VINAGR}" id="idVal"/>
										<core:Title text=""/>
										<Button text="{i18n>Search}" type="Emphasized" press="onSearchInquiryList"/>
										<Button text="{i18n>Reset}" press="onPressResetSearch"/>
									</f:content>
								</f:SimpleForm>
								<VBox class="sapUiLargeMarginBottom">
									<table:Table id="idAgreementTable" busy="{LocalDataModel>/busyIndAgrTable}" class="classRCPTable" selectionMode="Single"
										rows="{ path: 'LocalDataModel>/ZcEcpAgr'}" rowSelectionChange="onNavigate" selectionBehavior="Row" noData="{i18n>NoData}" showNoData="true">
										<table:columns>
											<table:Column >
												<Label text="{i18n>EcpAgreement}" textAlign="Center" width="100%"/>
												<table:template>
													<Text text="{path:'LocalDataModel>AgreementNumber'}" textAlign="Center" width="100%"/>
												</table:template>
											</table:Column>
											<table:Column >
												<Label text="{i18n>PlanCode}" textAlign="Center" width="100%"/>
												<table:template>
													<Text text="{path:'LocalDataModel>PlanType'}" textAlign="Center" width="100%"/>
												</table:template>
											</table:Column>
											<table:Column >
												<Label text="{i18n>Status}" textAlign="Center" width="100%"/>
												<table:template>
													<Text text="{path:'LocalDataModel>AgreementStatus'}" textAlign="Center" width="100%"/>
												</table:template>
											</table:Column>
											<table:Column >
												<Label text="{i18n>StatusDate}" textAlign="Center" width="100%"/>
												<table:template>
													<Text width="100%"
														text="{path:'LocalDataModel>StatusDate', type: 'sap.ui.model.type.Date', formatOptions: { pattern: 'yyyy-MM-dd', UTC: true }}"
														textAlign="Center"/>
												</table:template>
											</table:Column>
											<table:Column >
												<Label text="{i18n>ExpiryDate}" textAlign="Center" width="100%"/>
												<table:template>
													<Text width="100%"
														text="{path:'LocalDataModel>AgreementthruDate', type: 'sap.ui.model.type.Date', formatOptions: { pattern: 'yyyy-MM-dd', UTC: true }}"
														textAlign="Center"/>
												</table:template>
											</table:Column>
											<table:Column >
												<Label text="{i18n>ExpiryKm}" textAlign="Center" width="100%"/>
												<table:template>
													<Text text="{LocalDataModel>AgreementthruKMreading}" textAlign="Center" width="100%"/>
												</table:template>
											</table:Column>
											<table:Column >
												<Label text="{i18n>LienholderName}" textAlign="Center" width="100%"/>
												<table:template>
													<Text text="{path:'LocalDataModel>LienHolder'}" textAlign="Center" width="100%"/>
												</table:template>
											</table:Column>
											<table:Column >
												<Label text="{i18n>StatusReason}" textAlign="Center" width="100%"/>
												<table:template>
													<Text text="{path:'LocalDataModel>Agreementreasoncode', formatter : 'zecp.utils.formatter.fnFormatStatusReason'}" textAlign="Center"
														width="100%"/>
												</table:template>
											</table:Column>
										</table:columns>
									</table:Table>
								</VBox>
							</VBox>
						</uxap:blocks>
					</uxap:ObjectPageSubSection>
				</uxap:subSections>
			</uxap:ObjectPageSection>
		</uxap:sections>
	</uxap:ObjectPageLayout>
</mvc:View>